COPYING
MANIFEST.in
README.txt
setup.py
demo/tweetphotoUp.py
pyTweetPhoto/__init__.py
pyTweetPhoto/pyTweetPhoto.py
python_tweetphoto.egg-info/PKG-INFO
python_tweetphoto.egg-info/SOURCES.txt
python_tweetphoto.egg-info/dependency_links.txt
python_tweetphoto.egg-info/requires.txt
python_tweetphoto.egg-info/top_level.txt
