Metadata-Version: 1.0
Name: python-tweetphoto
Version: 0.2
Summary: A python wrapper around the TweetPhoto API
Home-page: http://code.google.com/p/python-tweetphoto/
Author: Marcel Caraciolo
Author-email: caraciol@gmail.com
License: GNU Library or Lesser General Public License (LGPL)
Download-URL: http://python-tweetphoto.googlecode.com/files/pyTweetPhoto-0.2.zip
Keywords: tweetphoto api
Platform: UNKNOWN
Classifier: Development Status :: 2 - Pre-Alpha
Classifier: Programming Language :: Python
Classifier: Intended Audience :: Developers
Classifier: Operating System :: OS Independent
Classifier: License :: OSI Approved :: GNU Library or Lesser General Public License (LGPL)
Classifier: Topic :: Software Development :: Libraries :: Python Modules
Classifier: Topic :: Communications :: File Sharing
Classifier: Topic :: Multimedia :: Graphics
Classifier: Topic :: Internet
